docs/Makefile
docs/__init__.py
docs/conf.py
docs/index.rst
docs/make.bat
magen_statistics_api/__init__.py
magen_statistics_api/counter_metric.py
magen_statistics_api/counter_metric_api.py
magen_statistics_api/metric.py
magen_statistics_api/metric_flavors.py
magen_statistics_server/__init__.py
magen_statistics_server/counter_urls.py
magen_statistics_server/counters.py
magen_statistics_server/metrics_app_rest_api.py
magen_statistics_server/metrics_server.py
magen_statistics_server/source_counter_rest_api.py
magen_statistics_server/statistics_main.py
magen_statistics_service-1.1a1.dist-info/DESCRIPTION.rst
magen_statistics_service-1.1a1.dist-info/METADATA
magen_statistics_service-1.1a1.dist-info/RECORD
magen_statistics_service-1.1a1.dist-info/WHEEL
magen_statistics_service-1.1a1.dist-info/metadata.json
magen_statistics_service-1.1a1.dist-info/top_level.txt
